silene/__init__.py
silene/browser_page.py
silene/cookie.py
silene/crawl_frontier.py
silene/crawl_request.py
silene/crawl_response.py
silene/crawler.py
silene/crawler_configuration.py
silene/element.py
silene/errors.py
silene-1.0.0.dist-info/METADATA
silene-1.0.0.dist-info/WHEEL
silene-1.0.0.dist-info/top_level.txt
silene-1.0.0.dist-info/RECORD
